cavd/__init__.py
cavd/area_volume.cpython-37m-x86_64-linux-gnu.so
cavd/batchskeletonstru.py
cavd/cavd_consts.py
cavd/channel.cpython-37m-x86_64-linux-gnu.so
cavd/channel_analysis.py
cavd/cluster.cpython-37m-x86_64-linux-gnu.so
cavd/cycle.cpython-37m-x86_64-linux-gnu.so
cavd/geometry.cpython-37m-x86_64-linux-gnu.so
cavd/get_Symmetry.py
cavd/graphstorage.cpython-37m-x86_64-linux-gnu.so
cavd/high_accuracy.cpython-37m-x86_64-linux-gnu.so
cavd/main.py
cavd/mergecluster.py
cavd/netinfo.cpython-37m-x86_64-linux-gnu.so
cavd/netio.cpython-37m-x86_64-linux-gnu.so
cavd/netstorage.cpython-37m-x86_64-linux-gnu.so
cavd/psd.cpython-37m-x86_64-linux-gnu.so
cavd/recovery.py
cavd/voronoicell.cpython-37m-x86_64-linux-gnu.so
cavd/modules/__init__.py
cavd/modules/bvmparam.dat
cavd/modules/ionic_radii.json
cavd/modules/ionic_radiianalysis.py
cavd/modules/oxidation_state.py
cavd/modules/struc_analysis.py
cavd-0.5.9.dist-info/METADATA
cavd-0.5.9.dist-info/WHEEL
cavd-0.5.9.dist-info/entry_points.txt
cavd-0.5.9.dist-info/top_level.txt
cavd-0.5.9.dist-info/RECORD
cavd.libs/libzeo++-50d07521.so
cavd.libs/libvoro++-e6a02302.so
