Metadata-Version: 2.1
Name: cavd
Version: 0.5.9
Summary: Crystal structure Analysis by Voronoi Decomposition
Home-page: https://www.bmaterials.cn
Author: HeBing
Author-email: shhebing@qq.com
License: UNKNOWN
Platform: UNKNOWN
Classifier: Programming Language :: Cython
Classifier: Programming Language :: C++
Classifier: Programming Language :: Python
Requires-Dist: Cython (>=0.29)
Requires-Dist: numpy (>=1.14.3)
Requires-Dist: spglib (>=1.9.9.44)
Requires-Dist: scipy (>=1.0.1)
Requires-Dist: pandas
Requires-Dist: monty (>=0.9.6)
Requires-Dist: networkx (>2.3)
Requires-Dist: mgtoolbox-kernel (>=0.1.2)
